README.rst
setup.py
src/mfpsync/__init__.py
src/mfpsync/http.py
src/mfpsync/main.py
src/mfpsync.egg-info/PKG-INFO
src/mfpsync.egg-info/SOURCES.txt
src/mfpsync.egg-info/dependency_links.txt
src/mfpsync.egg-info/entry_points.txt
src/mfpsync.egg-info/top_level.txt
src/mfpsync.egg-info/zip-safe
src/mfpsync/codec/__init__.py
src/mfpsync/codec/descriptors.py
src/mfpsync/codec/objects.py