Metadata-Version: 1.0
Name: mfpsync
Version: 0.1
Summary: Unofficial MyFitnessPal sync API client
Home-page: https://github.com/nathforge/mfpsync
Author: Nathan Reynolds
Author-email: email@nreynolds.co.uk
License: LICENSE.txt
Platform: UNKNOWN
